2021-06-30/sol.v
module ABC(
    ref, rxd, clock, reset_,
    led
);
    input clock, reset_;
    input rxd;
    input [4:0] ref;
    output [2:0] led;

    reg [2:0] LED;
    assign led = LED;

    reg [2:0] COUNT_BYTE;
    reg [3:0] COUNT_SPACE;
    reg [2:0] STAR;
    localparam 
        S0 = 0,
        S1 = 1,
        S2 = 2,
        S3 = 3,
        S4 = 4,
        S5 = 5;

    localparam mark = 1, space = 0;

    reg [7:0] BUFFER;

    always @(reset_ == 0) #1 begin
        STAR <= S0;
        LED <= 0;
        COUNT_SPACE <= 0;
        COUNT_BYTE <= 0;
        BUFFER <= 0;
    end

    always @(posedge clock) if(reset_ == 1) #3 begin
        casex (STAR)
            S0: begin
                STAR <= (rxd == mark) ? S0 : S1;
            end
            // Conto i bit di space (0)
            S1: begin
                COUNT_SPACE <= COUNT_SPACE+1;
                STAR <= (rxd == space) ? S1 : S2;
            end
            // Controllo se si tratta di bit 0 o 1
            S2: begin
                BUFFER <= (COUNT_SPACE[3]==1'b0) ? {mark,BUFFER[7:1]} : BUFFER;
                STAR <= (COUNT_SPACE[3]==1'b1) ? S3 : S4;       
            end
            // bit 0
            S3: begin
                BUFFER <= {space,BUFFER[7:1]};
                STAR <= S4;
            end
            S4: begin
                COUNT_SPACE <= 0;
                COUNT_BYTE <= COUNT_BYTE + 1;
                STAR <= (COUNT_BYTE == 7) ? S5 : S0;
            end
            // Trasmissione di led
            S5: begin
                LED <= (BUFFER[7:3] == ref) ? BUFFER[2:0] : LED;
                COUNT_BYTE <= 0;
                COUNT_SPACE <= 0;
                BUFFER <= 0;
                STAR <= S0;
            end
        endcase
    end


endmodule

2021-06-30/testbench.v
module testbench();

    wire clock;
    reg reset_;

    clock_generator clk(
        .clock(clock)
    );

    parameter mark = 1, space = 0; 
    reg rxd;

    reg [4:0] ref;
    wire [2:0] led;
    
    ABC dut (
        .led(led), .rxd(rxd), .ref(ref),
        .reset_(reset_), .clock(clock)
    );

    // Debug variables to highlight errors in waveform diagram
    reg error;

    initial
        begin
            $dumpfile("waveform.vcd");
            $dumpvars;

            error = 0;
            
            //the following structure is used to wait for expected signals, and fail if too much time passes
            fork : f
                begin
                    #100000;
                    $display("Timeout - waiting for signal failed");
                    disable f;
                end
            //actual tests start here
                begin
                    //reset phase
                    ref = 5'B01010;
                    rxd = mark;
                    reset_ = 0; #(clk.HALF_PERIOD);
                    
                    //first posedge
                    reset_ = 1;

                    fork
                        begin : transmitter
                            reg [3:0] i;

                            reg [7:0] byte;
                            reg [3:0] bit_idx;
                            reg [3:0] bit_len;
                            
                            for(i = 1; i < 8; i++) begin
                                if(i[0] == 0)
                                    // pari: valido
                                    byte = {ref, i[2:0]};
                                else
                                    // dispari: invalido
                                    byte = {~ref, i[2:0]};

                                // trasmissione di ciascun bit, a partire da LSB
                                for(bit_idx = 0; bit_idx < 8; bit_idx++) begin
                                    if(byte[bit_idx] == 1) 
                                        bit_len = 2 + ({byte, bit_idx} % 6);    // [2, 7]
                                    else
                                        bit_len = 11 + ({byte, bit_idx} % 5);   // [11, 15]
                                    
                                    rxd = space;
                                    #( bit_len * 2 * clk.HALF_PERIOD);
                                    rxd = mark;
                                    #( 20 * 2 * clk.HALF_PERIOD);
                                end
                            end
                        end
                        
                        begin : led_correctness
                            reg [3:0] i;
                            reg [2:0] expected;

                            for(i = 2; i < 8; i = i + 2) begin
                                @(led);
                                expected = i[2:0];

                                if(expected !== led) begin
                                    $display("Wrong output: expected %d, got %d instead", expected, led);
                                    error = 1;
                                end
                            end
                        end
                    join                   

                    disable f;
                end   
            join

            $finish;
        end

    always @(posedge error) #1
        error = 0;

endmodule

// generatore del segnale di clock
module clock_generator(
    clock
);
    output clock;

    parameter HALF_PERIOD = 5;

    reg CLOCK;
    assign clock = CLOCK;

    initial CLOCK <= 0;
    always #HALF_PERIOD CLOCK <= ~CLOCK;

endmodule

2021-06-30/waveform.vcd
$date
	Fri Jan 07 16:56:12 2022
$end
$version
	Icarus Verilog
$end
$timescale
	1s
$end
$scope module testbench $end
$var wire 3 ! led [2:0] $end
$var wire 1 " clock $end
$var reg 1 # error $end
$var reg 5 $ ref [4:0] $end
$var reg 1 % reset_ $end
$var reg 1 & rxd $end
$scope module clk $end
$var wire 1 " clock $end
$var reg 1 ' CLOCK $end
$upscope $end
$scope module dut $end
$var wire 1 " clock $end
$var wire 3 ( led [2:0] $end
$var wire 5 ) ref [4:0] $end
$var wire 1 % reset_ $end
$var wire 1 & rxd $end
$var reg 8 * BUFFER [7:0] $end
$var reg 3 + COUNT_BYTE [2:0] $end
$var reg 4 , COUNT_SPACE [3:0] $end
$var reg 3 - LED [2:0] $end
$var reg 3 . STAR [2:0] $end
$upscope $end
$scope fork f $end
$scope begin led_correctness $end
$var reg 3 / expected [2:0] $end
$var reg 4 0 i [3:0] $end
$upscope $end
$scope begin transmitter $end
$var reg 4 1 bit_idx [3:0] $end
$var reg 4 2 bit_len [3:0] $end
$var reg 8 3 byte [7:0] $end
$var reg 4 4 i [3:0] $end
$upscope $end
$upscope $end
$upscope $end
$enddefinitions $end
#0
$dumpvars
bx 4
bx 3
bx 2
bx 1
bx 0
bx /
bx .
bx -
bx ,
bx +
bx *
b1010 )
bx (
0'
1&
0%
b1010 $
0#
0"
bx !
$end
#1
b0 *
b0 +
b0 ,
b0 !
b0 (
b0 -
b0 .
#5
1"
1'
0&
b110 2
b0 1
b10101001 3
b1 4
b10 0
1%
#8
b1 .
#10
0"
0'
#15
1"
1'
#18
b1 ,
#20
0"
0'
#25
1"
1'
#28
b10 ,
#30
0"
0'
#35
1"
1'
#38
b11 ,
#40
0"
0'
#45
1"
1'
#48
b100 ,
#50
0"
0'
#55
1"
1'
#58
b101 ,
#60
0"
0'
#65
1"
1'
1&
#68
b10 .
b110 ,
#70
0"
0'
#75
1"
1'
#78
b100 .
b10000000 *
#80
0"
0'
#85
1"
1'
#88
b0 .
b1 +
b0 ,
#90
0"
0'
#95
1"
1'
#100
0"
0'
#105
1"
1'
#110
0"
0'
#115
1"
1'
#120
0"
0'
#125
1"
1'
#130
0"
0'
#135
1"
1'
#140
0"
0'
#145
1"
1'
#150
0"
0'
#155
1"
1'
#160
0"
0'
#165
1"
1'
#170
0"
0'
#175
1"
1'
#180
0"
0'
#185
1"
1'
#190
0"
0'
#195
1"
1'
#200
0"
0'
#205
1"
1'
#210
0"
0'
#215
1"
1'
#220
0"
0'
#225
1"
1'
#230
0"
0'
#235
1"
1'
#240
0"
0'
#245
1"
1'
#250
0"
0'
#255
1"
1'
#260
0"
0'
#265
1"
1'
0&
b1011 2
b1 1
#268
b1 .
#270
0"
0'
#275
1"
1'
#278
b1 ,
#280
0"
0'
#285
1"
1'
#288
b10 ,
#290
0"
0'
#295
1"
1'
#298
b11 ,
#300
0"
0'
#305
1"
1'
#308
b100 ,
#310
0"
0'
#315
1"
1'
#318
b101 ,
#320
0"
0'
#325
1"
1'
#328
b110 ,
#330
0"
0'
#335
1"
1'
#338
b111 ,
#340
0"
0'
#345
1"
1'
#348
b1000 ,
#350
0"
0'
#355
1"
1'
#358
b1001 ,
#360
0"
0'
#365
1"
1'
#368
b1010 ,
#370
0"
0'
#375
1"
1'
1&
#378
b10 .
b1011 ,
#380
0"
0'
#385
1"
1'
#388
b11 .
#390
0"
0'
#395
1"
1'
#398
b100 .
b1000000 *
#400
0"
0'
#405
1"
1'
#408
b0 .
b10 +
b0 ,
#410
0"
0'
#415
1"
1'
#420
0"
0'
#425
1"
1'
#430
0"
0'
#435
1"
1'
#440
0"
0'
#445
1"
1'
#450
0"
0'
#455
1"
1'
#460
0"
0'
#465
1"
1'
#470
0"
0'
#475
1"
1'
#480
0"
0'
#485
1"
1'
#490
0"
0'
#495
1"
1'
#500
0"
0'
#505
1"
1'
#510
0"
0'
#515
1"
1'
#520
0"
0'
#525
1"
1'
#530
0"
0'
#535
1"
1'
#540
0"
0'
#545
1"
1'
#550
0"
0'
#555
1"
1'
#560
0"
0'
#565
1"
1'
#570
0"
0'
#575
1"
1'
0&
b1100 2
b10 1
#578
b1 .
#580
0"
0'
#585
1"
1'
#588
b1 ,
#590
0"
0'
#595
1"
1'
#598
b10 ,
#600
0"
0'
#605
1"
1'
#608
b11 ,
#610
0"
0'
#615
1"
1'
#618
b100 ,
#620
0"
0'
#625
1"
1'
#628
b101 ,
#630
0"
0'
#635
1"
1'
#638
b110 ,
#640
0"
0'
#645
1"
1'
#648
b111 ,
#650
0"
0'
#655
1"
1'
#658
b1000 ,
#660
0"
0'
#665
1"
1'
#668
b1001 ,
#670
0"
0'
#675
1"
1'
#678
b1010 ,
#680
0"
0'
#685
1"
1'
#688
b1011 ,
#690
0"
0'
#695
1"
1'
1&
#698
b10 .
b1100 ,
#700
0"
0'
#705
1"
1'
#708
b11 .
#710
0"
0'
#715
1"
1'
#718
b100 .
b100000 *
#720
0"
0'
#725
1"
1'
#728
b0 .
b11 +
b0 ,
#730
0"
0'
#735
1"
1'
#740
0"
0'
#745
1"
1'
#750
0"
0'
#755
1"
1'
#760
0"
0'
#765
1"
1'
#770
0"
0'
#775
1"
1'
#780
0"
0'
#785
1"
1'
#790
0"
0'
#795
1"
1'
#800
0"
0'
#805
1"
1'
#810
0"
0'
#815
1"
1'
#820
0"
0'
#825
1"
1'
#830
0"
0'
#835
1"
1'
#840
0"
0'
#845
1"
1'
#850
0"
0'
#855
1"
1'
#860
0"
0'
#865
1"
1'
#870
0"
0'
#875
1"
1'
#880
0"
0'
#885
1"
1'
#890
0"
0'
#895
1"
1'
0&
b11 2
b11 1
#898
b1 .
#900
0"
0'
#905
1"
1'
#908
b1 ,
#910
0"
0'
#915
1"
1'
#918
b10 ,
#920
0"
0'
#925
1"
1'
1&
#928
b10 .
b11 ,
#930
0"
0'
#935
1"
1'
#938
b100 .
b10010000 *
#940
0"
0'
#945
1"
1'
#948
b0 .
b100 +
b0 ,
#950
0"
0'
#955
1"
1'
#960
0"
0'
#965
1"
1'
#970
0"
0'
#975
1"
1'
#980
0"
0'
#985
1"
1'
#990
0"
0'
#995
1"
1'
#1000
0"
0'
#1005
1"
1'
#1010
0"
0'
#1015
1"
1'
#1020
0"
0'
#1025
1"
1'
#1030
0"
0'
#1035
1"
1'
#1040
0"
0'
#1045
1"
1'
#1050
0"
0'
#1055
1"
1'
#1060
0"
0'
#1065
1"
1'
#1070
0"
0'
#1075
1"
1'
#1080
0"
0'
#1085
1"
1'
#1090
0"
0'
#1095
1"
1'
#1100
0"
0'
#1105
1"
1'
#1110
0"
0'
#1115
1"
1'
#1120
0"
0'
#1125
1"
1'
0&
b1110 2
b100 1
#1128
b1 .
#1130
0"
0'
#1135
1"
1'
#1138
b1 ,
#1140
0"
0'
#1145
1"
1'
#1148
b10 ,
#1150
0"
0'
#1155
1"
1'
#1158
b11 ,
#1160
0"
0'
#1165
1"
1'
#1168
b100 ,
#1170
0"
0'
#1175
1"
1'
#1178
b101 ,
#1180
0"
0'
#1185
1"
1'
#1188
b110 ,
#1190
0"
0'
#1195
1"
1'
#1198
b111 ,
#1200
0"
0'
#1205
1"
1'
#1208
b1000 ,
#1210
0"
0'
#1215
1"
1'
#1218
b1001 ,
#1220
0"
0'
#1225
1"
1'
#1228
b1010 ,
#1230
0"
0'
#1235
1"
1'
#1238
b1011 ,
#1240
0"
0'
#1245
1"
1'
#1248
b1100 ,
#1250
0"
0'
#1255
1"
1'
#1258
b1101 ,
#1260
0"
0'
#1265
1"
1'
1&
#1268
b10 .
b1110 ,
#1270
0"
0'
#1275
1"
1'
#1278
b11 .
#1280
0"
0'
#1285
1"
1'
#1288
b100 .
b1001000 *
#1290
0"
0'
#1295
1"
1'
#1298
b0 .
b101 +
b0 ,
#1300
0"
0'
#1305
1"
1'
#1310
0"
0'
#1315
1"
1'
#1320
0"
0'
#1325
1"
1'
#1330
0"
0'
#1335
1"
1'
#1340
0"
0'
#1345
1"
1'
#1350
0"
0'
#1355
1"
1'
#1360
0"
0'
#1365
1"
1'
#1370
0"
0'
#1375
1"
1'
#1380
0"
0'
#1385
1"
1'
#1390
0"
0'
#1395
1"
1'
#1400
0"
0'
#1405
1"
1'
#1410
0"
0'
#1415
1"
1'
#1420
0"
0'
#1425
1"
1'
#1430
0"
0'
#1435
1"
1'
#1440
0"
0'
#1445
1"
1'
#1450
0"
0'
#1455
1"
1'
#1460
0"
0'
#1465
1"
1'
0&
b101 2
b101 1
#1468
b1 .
#1470
0"
0'
#1475
1"
1'
#1478
b1 ,
#1480
0"
0'
#1485
1"
1'
#1488
b10 ,
#1490
0"
0'
#1495
1"
1'
#1498
b11 ,
#1500
0"
0'
#1505
1"
1'
#1508
b100 ,
#1510
0"
0'
#1515
1"
1'
1&
#1518
b10 .
b101 ,
#1520
0"
0'
#1525
1"
1'
#1528
b100 .
b10100100 *
#1530
0"
0'
#1535
1"
1'
#1538
b0 .
b110 +
b0 ,
#1540
0"
0'
#1545
1"
1'
#1550
0"
0'
#1555
1"
1'
#1560
0"
0'
#1565
1"
1'
#1570
0"
0'
#1575
1"
1'
#1580
0"
0'
#1585
1"
1'
#1590
0"
0'
#1595
1"
1'
#1600
0"
0'
#1605
1"
1'
#1610
0"
0'
#1615
1"
1'
#1620
0"
0'
#1625
1"
1'
#1630
0"
0'
#1635
1"
1'
#1640
0"
0'
#1645
1"
1'
#1650
0"
0'
#1655
1"
1'
#1660
0"
0'
#1665
1"
1'
#1670
0"
0'
#1675
1"
1'
#1680
0"
0'
#1685
1"
1'
#1690
0"
0'
#1695
1"
1'
#1700
0"
0'
#1705
1"
1'
#1710
0"
0'
#1715
1"
1'
0&
b1011 2
b110 1
#1718
b1 .
#1720
0"
0'
#1725
1"
1'
#1728
b1 ,
#1730
0"
0'
#1735
1"
1'
#1738
b10 ,
#1740
0"
0'
#1745
1"
1'
#1748
b11 ,
#1750
0"
0'
#1755
1"
1'
#1758
b100 ,
#1760
0"
0'
#1765
1"
1'
#1768
b101 ,
#1770
0"
0'
#1775
1"
1'
#1778
b110 ,
#1780
0"
0'
#1785
1"
1'
#1788
b111 ,
#1790
0"
0'
#1795
1"
1'
#1798
b1000 ,
#1800
0"
0'
#1805
1"
1'
#1808
b1001 ,
#1810
0"
0'
#1815
1"
1'
#1818
b1010 ,
#1820
0"
0'
#1825
1"
1'
1&
#1828
b10 .
b1011 ,
#1830
0"
0'
#1835
1"
1'
#1838
b11 .
#1840
0"
0'
#1845
1"
1'
#1848
b100 .
b1010010 *
#1850
0"
0'
#1855
1"
1'
#1858
b0 .
b111 +
b0 ,
#1860
0"
0'
#1865
1"
1'
#1870
0"
0'
#1875
1"
1'
#1880
0"
0'
#1885
1"
1'
#1890
0"
0'
#1895
1"
1'
#1900
0"
0'
#1905
1"
1'
#1910
0"
0'
#1915
1"
1'
#1920
0"
0'
#1925
1"
1'
#1930
0"
0'
#1935
1"
1'
#1940
0"
0'
#1945
1"
1'
#1950
0"
0'
#1955
1"
1'
#1960
0"
0'
#1965
1"
1'
#1970
0"
0'
#1975
1"
1'
#1980
0"
0'
#1985
1"
1'
#1990
0"
0'
#1995
1"
1'
#2000
0"
0'
#2005
1"
1'
#2010
0"
0'
#2015
1"
1'
#2020
0"
0'
#2025
1"
1'
0&
b111 2
b111 1
#2028
b1 .
#2030
0"
0'
#2035
1"
1'
#2038
b1 ,
#2040
0"
0'
#2045
1"
1'
#2048
b10 ,
#2050
0"
0'
#2055
1"
1'
#2058
b11 ,
#2060
0"
0'
#2065
1"
1'
#2068
b100 ,
#2070
0"
0'
#2075
1"
1'
#2078
b101 ,
#2080
0"
0'
#2085
1"
1'
#2088
b110 ,
#2090
0"
0'
#2095
1"
1'
1&
#2098
b10 .
b111 ,
#2100
0"
0'
#2105
1"
1'
#2108
b100 .
b10101001 *
#2110
0"
0'
#2115
1"
1'
#2118
b101 .
b0 +
b0 ,
#2120
0"
0'
#2125
1"
1'
#2128
b0 .
b0 *
#2130
0"
0'
#2135
1"
1'
#2140
0"
0'
#2145
1"
1'
#2150
0"
0'
#2155
1"
1'
#2160
0"
0'
#2165
1"
1'
#2170
0"
0'
#2175
1"
1'
#2180
0"
0'
#2185
1"
1'
#2190
0"
0'
#2195
1"
1'
#2200
0"
0'
#2205
1"
1'
#2210
0"
0'
#2215
1"
1'
#2220
0"
0'
#2225
1"
1'
#2230
0"
0'
#2235
1"
1'
#2240
0"
0'
#2245
1"
1'
#2250
0"
0'
#2255
1"
1'
#2260
0"
0'
#2265
1"
1'
#2270
0"
0'
#2275
1"
1'
#2280
0"
0'
#2285
1"
1'
#2290
0"
0'
#2295
1"
1'
0&
b1101 2
b1010010 3
b10 4
b0 1
#2298
b1 .
#2300
0"
0'
#2305
1"
1'
#2308
b1 ,
#2310
0"
0'
#2315
1"
1'
#2318
b10 ,
#2320
0"
0'
#2325
1"
1'
#2328
b11 ,
#2330
0"
0'
#2335
1"
1'
#2338
b100 ,
#2340
0"
0'
#2345
1"
1'
#2348
b101 ,
#2350
0"
0'
#2355
1"
1'
#2358
b110 ,
#2360
0"
0'
#2365
1"
1'
#2368
b111 ,
#2370
0"
0'
#2375
1"
1'
#2378
b1000 ,
#2380
0"
0'
#2385
1"
1'
#2388
b1001 ,
#2390
0"
0'
#2395
1"
1'
#2398
b1010 ,
#2400
0"
0'
#2405
1"
1'
#2408
b1011 ,
#2410
0"
0'
#2415
1"
1'
#2418
b1100 ,
#2420
0"
0'
#2425
1"
1'
1&
#2428
b10 .
b1101 ,
#2430
0"
0'
#2435
1"
1'
#2438
b11 .
#2440
0"
0'
#2445
1"
1'
#2448
b100 .
#2450
0"
0'
#2455
1"
1'
#2458
b0 .
b1 +
b0 ,
#2460
0"
0'
#2465
1"
1'
#2470
0"
0'
#2475
1"
1'
#2480
0"
0'
#2485
1"
1'
#2490
0"
0'
#2495
1"
1'
#2500
0"
0'
#2505
1"
1'
#2510
0"
0'
#2515
1"
1'
#2520
0"
0'
#2525
1"
1'
#2530
0"
0'
#2535
1"
1'
#2540
0"
0'
#2545
1"
1'
#2550
0"
0'
#2555
1"
1'
#2560
0"
0'
#2565
1"
1'
#2570
0"
0'
#2575
1"
1'
#2580
0"
0'
#2585
1"
1'
#2590
0"
0'
#2595
1"
1'
#2600
0"
0'
#2605
1"
1'
#2610
0"
0'
#2615
1"
1'
#2620
0"
0'
#2625
1"
1'
0&
b111 2
b1 1
#2628
b1 .
#2630
0"
0'
#2635
1"
1'
#2638
b1 ,
#2640
0"
0'
#2645
1"
1'
#2648
b10 ,
#2650
0"
0'
#2655
1"
1'
#2658
b11 ,
#2660
0"
0'
#2665
1"
1'
#2668
b100 ,
#2670
0"
0'
#2675
1"
1'
#2678
b101 ,
#2680
0"
0'
#2685
1"
1'
#2688
b110 ,
#2690
0"
0'
#2695
1"
1'
1&
#2698
b10 .
b111 ,
#2700
0"
0'
#2705
1"
1'
#2708
b100 .
b10000000 *
#2710
0"
0'
#2715
1"
1'
#2718
b0 .
b10 +
b0 ,
#2720
0"
0'
#2725
1"
1'
#2730
0"
0'
#2735
1"
1'
#2740
0"
0'
#2745
1"
1'
#2750
0"
0'
#2755
1"
1'
#2760
0"
0'
#2765
1"
1'
#2770
0"
0'
#2775
1"
1'
#2780
0"
0'
#2785
1"
1'
#2790
0"
0'
#2795
1"
1'
#2800
0"
0'
#2805
1"
1'
#2810
0"
0'
#2815
1"
1'
#2820
0"
0'
#2825
1"
1'
#2830
0"
0'
#2835
1"
1'
#2840
0"
0'
#2845
1"
1'
#2850
0"
0'
#2855
1"
1'
#2860
0"
0'
#2865
1"
1'
#2870
0"
0'
#2875
1"
1'
#2880
0"
0'
#2885
1"
1'
#2890
0"
0'
#2895
1"
1'
0&
b1111 2
b10 1
#2898
b1 .
#2900
0"
0'
#2905
1"
1'
#2908
b1 ,
#2910
0"
0'
#2915
1"
1'
#2918
b10 ,
#2920
0"
0'
#2925
1"
1'
#2928
b11 ,
#2930
0"
0'
#2935
1"
1'
#2938
b100 ,
#2940
0"
0'
#2945
1"
1'
#2948
b101 ,
#2950
0"
0'
#2955
1"
1'
#2958
b110 ,
#2960
0"
0'
#2965
1"
1'
#2968
b111 ,
#2970
0"
0'
#2975
1"
1'
#2978
b1000 ,
#2980
0"
0'
#2985
1"
1'
#2988
b1001 ,
#2990
0"
0'
#2995
1"
1'
#2998
b1010 ,
#3000
0"
0'
#3005
1"
1'
#3008
b1011 ,
#3010
0"
0'
#3015
1"
1'
#3018
b1100 ,
#3020
0"
0'
#3025
1"
1'
#3028
b1101 ,
#3030
0"
0'
#3035
1"
1'
#3038
b1110 ,
#3040
0"
0'
#3045
1"
1'
1&
#3048
b10 .
b1111 ,
#3050
0"
0'
#3055
1"
1'
#3058
b11 .
#3060
0"
0'
#3065
1"
1'
#3068
b100 .
b1000000 *
#3070
0"
0'
#3075
1"
1'
#3078
b0 .
b11 +
b0 ,
#3080
0"
0'
#3085
1"
1'
#3090
0"
0'
#3095
1"
1'
#3100
0"
0'
#3105
1"
1'
#3110
0"
0'
#3115
1"
1'
#3120
0"
0'
#3125
1"
1'
#3130
0"
0'
#3135
1"
1'
#3140
0"
0'
#3145
1"
1'
#3150
0"
0'
#3155
1"
1'
#3160
0"
0'
#3165
1"
1'
#3170
0"
0'
#3175
1"
1'
#3180
0"
0'
#3185
1"
1'
#3190
0"
0'
#3195
1"
1'
#3200
0"
0'
#3205
1"
1'
#3210
0"
0'
#3215
1"
1'
#3220
0"
0'
#3225
1"
1'
#3230
0"
0'
#3235
1"
1'
#3240
0"
0'
#3245
1"
1'
0&
b1011 2
b11 1
#3248
b1 .
#3250
0"
0'
#3255
1"
1'
#3258
b1 ,
#3260
0"
0'
#3265
1"
1'
#3268
b10 ,
#3270
0"
0'
#3275
1"
1'
#3278
b11 ,
#3280
0"
0'
#3285
1"
1'
#3288
b100 ,
#3290
0"
0'
#3295
1"
1'
#3298
b101 ,
#3300
0"
0'
#3305
1"
1'
#3308
b110 ,
#3310
0"
0'
#3315
1"
1'
#3318
b111 ,
#3320
0"
0'
#3325
1"
1'
#3328
b1000 ,
#3330
0"
0'
#3335
1"
1'
#3338
b1001 ,
#3340
0"
0'
#3345
1"
1'
#3348
b1010 ,
#3350
0"
0'
#3355
1"
1'
1&
#3358
b10 .
b1011 ,
#3360
0"
0'
#3365
1"
1'
#3368
b11 .
#3370
0"
0'
#3375
1"
1'
#3378
b100 .
b100000 *
#3380
0"
0'
#3385
1"
1'
#3388
b0 .
b100 +
b0 ,
#3390
0"
0'
#3395
1"
1'
#3400
0"
0'
#3405
1"
1'
#3410
0"
0'
#3415
1"
1'
#3420
0"
0'
#3425
1"
1'
#3430
0"
0'
#3435
1"
1'
#3440
0"
0'
#3445
1"
1'
#3450
0"
0'
#3455
1"
1'
#3460
0"
0'
#3465
1"
1'
#3470
0"
0'
#3475
1"
1'
#3480
0"
0'
#3485
1"
1'
#3490
0"
0'
#3495
1"
1'
#3500
0"
0'
#3505
1"
1'
#3510
0"
0'
#3515
1"
1'
#3520
0"
0'
#3525
1"
1'
#3530
0"
0'
#3535
1"
1'
#3540
0"
0'
#3545
1"
1'
#3550
0"
0'
#3555
1"
1'
0&
b100 2
b100 1
#3558
b1 .
#3560
0"
0'
#3565
1"
1'
#3568
b1 ,
#3570
0"
0'
#3575
1"
1'
#3578
b10 ,
#3580
0"
0'
#3585
1"
1'
#3588
b11 ,
#3590
0"
0'
#3595
1"
1'
1&
#3598
b10 .
b100 ,
#3600
0"
0'
#3605
1"
1'
#3608
b100 .
b10010000 *
#3610
0"
0'
#3615
1"
1'
#3618
b0 .
b101 +
b0 ,
#3620
0"
0'
#3625
1"
1'
#3630
0"
0'
#3635
1"
1'
#3640
0"
0'
#3645
1"
1'
#3650
0"
0'
#3655
1"
1'
#3660
0"
0'
#3665
1"
1'
#3670
0"
0'
#3675
1"
1'
#3680
0"
0'
#3685
1"
1'
#3690
0"
0'
#3695
1"
1'
#3700
0"
0'
#3705
1"
1'
#3710
0"
0'
#3715
1"
1'
#3720
0"
0'
#3725
1"
1'
#3730
0"
0'
#3735
1"
1'
#3740
0"
0'
#3745
1"
1'
#3750
0"
0'
#3755
1"
1'
#3760
0"
0'
#3765
1"
1'
#3770
0"
0'
#3775
1"
1'
#3780
0"
0'
#3785
1"
1'
#3790
0"
0'
#3795
1"
1'
0&
b1101 2
b101 1
#3798
b1 .
#3800
0"
0'
#3805
1"
1'
#3808
b1 ,
#3810
0"
0'
#3815
1"
1'
#3818
b10 ,
#3820
0"
0'
#3825
1"
1'
#3828
b11 ,
#3830
0"
0'
#3835
1"
1'
#3838
b100 ,
#3840
0"
0'
#3845
1"
1'
#3848
b101 ,
#3850
0"
0'
#3855
1"
1'
#3858
b110 ,
#3860
0"
0'
#3865
1"
1'
#3868
b111 ,
#3870
0"
0'
#3875
1"
1'
#3878
b1000 ,
#3880
0"
0'
#3885
1"
1'
#3888
b1001 ,
#3890
0"
0'
#3895
1"
1'
#3898
b1010 ,
#3900
0"
0'
#3905
1"
1'
#3908
b1011 ,
#3910
0"
0'
#3915
1"
1'
#3918
b1100 ,
#3920
0"
0'
#3925
1"
1'
1&
#3928
b10 .
b1101 ,
#3930
0"
0'
#3935
1"
1'
#3938
b11 .
#3940
0"
0'
#3945
1"
1'
#3948
b100 .
b1001000 *
#3950
0"
0'
#3955
1"
1'
#3958
b0 .
b110 +
b0 ,
#3960
0"
0'
#3965
1"
1'
#3970
0"
0'
#3975
1"
1'
#3980
0"
0'
#3985
1"
1'
#3990
0"
0'
#3995
1"
1'
#4000
0"
0'
#4005
1"
1'
#4010
0"
0'
#4015
1"
1'
#4020
0"
0'
#4025
1"
1'
#4030
0"
0'
#4035
1"
1'
#4040
0"
0'
#4045
1"
1'
#4050
0"
0'
#4055
1"
1'
#4060
0"
0'
#4065
1"
1'
#4070
0"
0'
#4075
1"
1'
#4080
0"
0'
#4085
1"
1'
#4090
0"
0'
#4095
1"
1'
#4100
0"
0'
#4105
1"
1'
#4110
0"
0'
#4115
1"
1'
#4120
0"
0'
#4125
1"
1'
0&
b110 2
b110 1
#4128
b1 .
#4130
0"
0'
#4135
1"
1'
#4138
b1 ,
#4140
0"
0'
#4145
1"
1'
#4148
b10 ,
#4150
0"
0'
#4155
1"
1'
#4158
b11 ,
#4160
0"
0'
#4165
1"
1'
#4168
b100 ,
#4170
0"
0'
#4175
1"
1'
#4178
b101 ,
#4180
0"
0'
#4185
1"
1'
1&
#4188
b10 .
b110 ,
#4190
0"
0'
#4195
1"
1'
#4198
b100 .
b10100100 *
#4200
0"
0'
#4205
1"
1'
#4208
b0 .
b111 +
b0 ,
#4210
0"
0'
#4215
1"
1'
#4220
0"
0'
#4225
1"
1'
#4230
0"
0'
#4235
1"
1'
#4240
0"
0'
#4245
1"
1'
#4250
0"
0'
#4255
1"
1'
#4260
0"
0'
#4265
1"
1'
#4270
0"
0'
#4275
1"
1'
#4280
0"
0'
#4285
1"
1'
#4290
0"
0'
#4295
1"
1'
#4300
0"
0'
#4305
1"
1'
#4310
0"
0'
#4315
1"
1'
#4320
0"
0'
#4325
1"
1'
#4330
0"
0'
#4335
1"
1'
#4340
0"
0'
#4345
1"
1'
#4350
0"
0'
#4355
1"
1'
#4360
0"
0'
#4365
1"
1'
#4370
0"
0'
#4375
1"
1'
#4380
0"
0'
#4385
1"
1'
0&
b1111 2
b111 1
#4388
b1 .
#4390
0"
0'
#4395
1"
1'
#4398
b1 ,
#4400
0"
0'
#4405
1"
1'
#4408
b10 ,
#4410
0"
0'
#4415
1"
1'
#4418
b11 ,
#4420
0"
0'
#4425
1"
1'
#4428
b100 ,
#4430
0"
0'
#4435
1"
1'
#4438
b101 ,
#4440
0"
0'
#4445
1"
1'
#4448
b110 ,
#4450
0"
0'
#4455
1"
1'
#4458
b111 ,
#4460
0"
0'
#4465
1"
1'
#4468
b1000 ,
#4470
0"
0'
#4475
1"
1'
#4478
b1001 ,
#4480
0"
0'
#4485
1"
1'
#4488
b1010 ,
#4490
0"
0'
#4495
1"
1'
#4498
b1011 ,
#4500
0"
0'
#4505
1"
1'
#4508
b1100 ,
#4510
0"
0'
#4515
1"
1'
#4518
b1101 ,
#4520
0"
0'
#4525
1"
1'
#4528
b1110 ,
#4530
0"
0'
#4535
1"
1'
1&
#4538
b10 .
b1111 ,
#4540
0"
0'
#4545
1"
1'
#4548
b11 .
#4550
0"
0'
#4555
1"
1'
#4558
b100 .
b1010010 *
#4560
0"
0'
#4565
1"
1'
#4568
b101 .
b0 +
b0 ,
#4570
0"
0'
#4575
1"
1'
#4578
b100 0
b10 /
b0 .
b0 *
b10 !
b10 (
b10 -
#4580
0"
0'
#4585
1"
1'
#4590
0"
0'
#4595
1"
1'
#4600
0"
0'
#4605
1"
1'
#4610
0"
0'
#4615
1"
1'
#4620
0"
0'
#4625
1"
1'
#4630
0"
0'
#4635
1"
1'
#4640
0"
0'
#4645
1"
1'
#4650
0"
0'
#4655
1"
1'
#4660
0"
0'
#4665
1"
1'
#4670
0"
0'
#4675
1"
1'
#4680
0"
0'
#4685
1"
1'
#4690
0"
0'
#4695
1"
1'
#4700
0"
0'
#4705
1"
1'
#4710
0"
0'
#4715
1"
1'
#4720
0"
0'
#4725
1"
1'
#4730
0"
0'
#4735
1"
1'
0&
b10 2
b10101011 3
b11 4
b0 1
#4738
b1 .
#4740
0"
0'
#4745
1"
1'
#4748
b1 ,
#4750
0"
0'
#4755
1"
1'
1&
#4758
b10 .
b10 ,
#4760
0"
0'
#4765
1"
1'
#4768
b100 .
b10000000 *
#4770
0"
0'
#4775
1"
1'
#4778
b0 .
b1 +
b0 ,
#4780
0"
0'
#4785
1"
1'
#4790
0"
0'
#4795
1"
1'
#4800
0"
0'
#4805
1"
1'
#4810
0"
0'
#4815
1"
1'
